llama_stack_provider_kft/__init__.py
llama_stack_provider_kft/config.py
llama_stack_provider_kft/kft_adapter.py
llama_stack_provider_kft/provider.py
llama_stack_provider_kft-0.1.0.dist-info/licenses/LICENSE
llama_stack_provider_kft-0.1.0.dist-info/METADATA
llama_stack_provider_kft-0.1.0.dist-info/WHEEL
llama_stack_provider_kft-0.1.0.dist-info/top_level.txt
llama_stack_provider_kft-0.1.0.dist-info/RECORD
