Metadata-Version: 2.4
Name: llama-stack-provider-kft
Version: 0.1.0
Summary: Llama Stack Provider for Distributed InstructLab Training using KFT
Requires-Python: >=3.10
License-File: LICENSE
Requires-Dist: llama-stack>=0.2.3
Requires-Dist: kubeflow-training==1.9.1
Requires-Dist: kubernetes
Requires-Dist: urllib3
Requires-Dist: six
Requires-Dist: pydantic
Requires-Dist: aiohttp
Requires-Dist: aiosqlite
Requires-Dist: datasets
Requires-Dist: fastapi
Requires-Dist: httpx
Requires-Dist: numpy
Requires-Dist: openai
Requires-Dist: opentelemetry-exporter-otlp-proto-http
Requires-Dist: opentelemetry-sdk
Requires-Dist: requests
Requires-Dist: uvicorn
Dynamic: license-file
